setup.py
lands/__init__.py
lands/basic_map_operations.py
lands/biome.py
lands/common.py
lands/draw.py
lands/drawing_functions.py
lands/erosion_generator.py
lands/generator.py
lands/geo.py
lands/plates.py
lands/step.py
lands/version.py
lands/water_generator.py
lands/world.py
lands.egg-info/PKG-INFO
lands.egg-info/SOURCES.txt
lands.egg-info/dependency_links.txt
lands.egg-info/entry_points.txt
lands.egg-info/requires.txt
lands.egg-info/top_level.txt
lands/gui/__init__.py
lands/gui/main.py
lands/gui/view.py
lands/protobuf/World_pb2.py
lands/protobuf/__init__.py
lands/simulations/BiomeSimulation.py
lands/simulations/ErosionSimulation.py
lands/simulations/HumiditySimulation.py
lands/simulations/IrrigationSimulation.py
lands/simulations/PermeabilitySimulation.py
lands/simulations/TemperatureSimulation.py
lands/simulations/WatermapSimulation.py
lands/simulations/__init__.py
lands/simulations/basic.py