Metadata-Version: 1.1
Name: lands
Version: 0.5.3.1
Summary: World generator simulating plate tectonics, erosion, etc.
Home-page: http://github.com/ftomassetti/lands
Author: Federico Tomassetti
Author-email: f.tomassetti@gmail.com
License: UNKNOWN
Download-URL: http://github.com/ftomassetti/lands
Platform: UNKNOWN
